wordle_pycli/__init__.py
wordle_pycli/allowed_words.py
wordle_pycli/wordle.py
wordle_pycli-0.0.3.dist-info/LICENSE
wordle_pycli-0.0.3.dist-info/METADATA
wordle_pycli-0.0.3.dist-info/WHEEL
wordle_pycli-0.0.3.dist-info/entry_points.txt
wordle_pycli-0.0.3.dist-info/top_level.txt
wordle_pycli-0.0.3.dist-info/RECORD
