Metadata-Version: 2.1
Name: wordle-pycli
Version: 0.0.3
Summary: Play Wordle Anywhere, Anytime - Unleash Your Vocabulary Adventure!
Home-page: https://github.com/Qazalbash/wordle-pycli
Author: Meesum Qazalbash
Author-email: meesumqazalbash@gmail.com
License: MIT
Keywords: wordle,cli,game,word game,wordle game,wordle-cli
Classifier: Programming Language :: Python :: 3
Classifier: License :: OSI Approved :: MIT License
Classifier: Operating System :: OS Independent
Classifier: Environment :: Console
Classifier: Topic :: Games/Entertainment :: Puzzle Games
Requires-Python: >=3.6
License-File: LICENSE
